badfiles/__init__.py
badfiles/badfiles.py
badfiles/cli.py
badfiles/process_tar.py
badfiles/rules/csv_rules.yara
badfiles/rules/id_rules.yara
badfiles/rules/tar_rules.yara
badfiles/rules/zip_rules.yara
badfiles/utils.py
badfiles-0.3.0.dist-info/entry_points.txt
badfiles-0.3.0.dist-info/LICENSE
badfiles-0.3.0.dist-info/WHEEL
badfiles-0.3.0.dist-info/METADATA
badfiles-0.3.0.dist-info/RECORD
